{
  "history": [
    {
      "datum": "2026-07-09",
      "depot_gesamt": 9769.26,
      "etf_gesamt": null,
      "cash_depot": null,
      "cash_etf": null,
      "dax": 25118.27,
      "msci": 125.71
    },
    {
      "datum": "2026-07-23",
      "depot_gesamt": 9532.18,
      "etf_gesamt": 4898.49,
      "cash_depot": 25.88,
      "cash_etf": 147.47,
      "dax": 24753.69,
      "msci": 124.48
    },
    {
      "datum": "2026-07-24",
      "depot_gesamt": 9575.31,
      "etf_gesamt": 4915.46,
      "cash_depot": 25.88,
      "cash_etf": 147.47,
      "dax": 25064.94,
      "msci": 125.235
    }
  ]
}